qiskit_ibm_transpiler_mcp_server/__init__.py
qiskit_ibm_transpiler_mcp_server/py.typed
qiskit_ibm_transpiler_mcp_server/qiskit_runtime_service_provider.py
qiskit_ibm_transpiler_mcp_server/qta.py
qiskit_ibm_transpiler_mcp_server/server.py
qiskit_ibm_transpiler_mcp_server/utils.py
qiskit_ibm_transpiler_mcp_server-0.2.0.dist-info/METADATA
qiskit_ibm_transpiler_mcp_server-0.2.0.dist-info/WHEEL
qiskit_ibm_transpiler_mcp_server-0.2.0.dist-info/entry_points.txt
qiskit_ibm_transpiler_mcp_server-0.2.0.dist-info/RECORD
