Metadata-Version: 2.4
Name: qiskit-ibm-transpiler-mcp-server
Version: 0.2.0
Summary: MCP server for AI Transpiler IBM Quantum services through local and Qiskit IBM Runtime executions
Project-URL: Homepage, https://github.com/Qiskit/mcp-servers
Project-URL: Repository, https://github.com/Qiskit/mcp-servers
Project-URL: Documentation, https://github.com/Qiskit/mcp-servers/tree/main/qiskit-ibm-transpiler-mcp-server#readme
Project-URL: Bug Tracker, https://github.com/Qiskit/mcp-servers/issues
Author-email: Qiskit Community <qiskit@us.ibm.com>
License: Apache-2.0
Requires-Python: <3.14,>=3.10
Requires-Dist: fastmcp>=2.12.4
Requires-Dist: nest-asyncio>=1.5.0
Requires-Dist: qiskit-ibm-transpiler>=0.15.0
Requires-Dist: qiskit-mcp-server
Provides-Extra: all
Requires-Dist: bandit[toml]>=1.9.2; extra == 'all'
Requires-Dist: mypy>=1.15.0; extra == 'all'
Requires-Dist: pytest-asyncio>=1.2.0; extra == 'all'
Requires-Dist: pytest-cov>=4.1.0; extra == 'all'
Requires-Dist: pytest-mock>=3.15.1; extra == 'all'
Requires-Dist: pytest>=8.4.2; extra == 'all'
Requires-Dist: ruff>=0.11.13; extra == 'all'
Provides-Extra: dev
Requires-Dist: mypy>=1.15.0; extra == 'dev'
Requires-Dist: ruff>=0.11.13; extra == 'dev'
Provides-Extra: test
Requires-Dist: bandit[toml]>=1.9.2; extra == 'test'
Requires-Dist: pytest-asyncio>=1.2.0; extra == 'test'
Requires-Dist: pytest-cov>=4.1.0; extra == 'test'
Requires-Dist: pytest-mock>=3.15.1; extra == 'test'
Requires-Dist: pytest>=8.4.2; extra == 'test'
